cmn/__init__.py
cmn/__main__.py
cmn/test_main.py
cmn/change_media_name/change_media_name.py
cmn/colored_logger/colored_logger.py
cmn/output_formatter/output_formatter.py
cmn/output_formatter/test_output_formatter.py
cmn-2.0.0.dist-info/entry_points.txt
cmn-2.0.0.dist-info/LICENSE
cmn-2.0.0.dist-info/WHEEL
cmn-2.0.0.dist-info/METADATA
cmn-2.0.0.dist-info/RECORD
