Metadata-Version: 2.1
Name: cmn
Version: 2.0.0
Summary: Main - Module responsible for the main program. Parses the arguments and calls the other modules.
Author-email: Henrique Alvelos <henriquealvelos@gmail.com>
Requires-Python: >=3.10
Classifier: License :: OSI Approved :: Apache Software License
Requires-Dist: colorama >= 0.4.6
Project-URL: Home, https://github.com/Henrique-190/CMN
